node_db/__init__.py
node_db/database.py
node_db/models/__init__.py
node_db/models/auth.py
node_db/models/base.py
node_db/models/gopacs.py
node_db/models/public.py
node_db-0.1.4.dist-info/METADATA
node_db-0.1.4.dist-info/WHEEL
node_db-0.1.4.dist-info/top_level.txt
node_db-0.1.4.dist-info/RECORD
