Metadata-Version: 2.2
Name: node-db
Version: 0.1.4
Summary: The shared database for Node
Author: Node
Requires-Dist: sqlalchemy>=2.0.0
Requires-Dist: python-dotenv>=1.0.0
Requires-Dist: psycopg2-binary>=2.9.0
Dynamic: author
Dynamic: requires-dist
Dynamic: summary
